{
    "number": 100,
    "name": "العَادِيَاتِ",
    "transliteration": "Al-Aadiyaat",
    "translation": "The Chargers",
    "revelation_type": "Meccan",
    "total_verses": 11,
    "verses": [
        {
            "Verses": 1,
            "text": "بِسْمِ اللَّهِ الرَّحْمَٰنِ الرَّحِيمِ وَالْعَادِيَاتِ ضَبْحًا"
        },
        {
            "Verses": 2,
            "text": "فَالْمُورِيَاتِ قَدْحًا"
        },
        {
            "Verses": 3,
            "text": "فَالْمُغِيرَاتِ صُبْحًا"
        },
        {
            "Verses": 4,
            "text": "فَأَثَرْنَ بِهِ نَقْعًا"
        },
        {
            "Verses": 5,
            "text": "فَوَسَطْنَ بِهِ جَمْعًا"
        },
        {
            "Verses": 6,
            "text": "إِنَّ الْإِنْسَانَ لِرَبِّهِ لَكَنُودٌ"
        },
        {
            "Verses": 7,
            "text": "وَإِنَّهُ عَلَىٰ ذَٰلِكَ لَشَهِيدٌ"
        },
        {
            "Verses": 8,
            "text": "وَإِنَّهُ لِحُبِّ الْخَيْرِ لَشَدِيدٌ"
        },
        {
            "Verses": 9,
            "text": "۞ أَفَلَا يَعْلَمُ إِذَا بُعْثِرَ مَا فِي الْقُبُورِ"
        },
        {
            "Verses": 10,
            "text": "وَحُصِّلَ مَا فِي الصُّدُورِ"
        },
        {
            "Verses": 11,
            "text": "إِنَّ رَبَّهُمْ بِهِمْ يَوْمَئِذٍ لَخَبِيرٌ"
        }
    ]
}
